{
  "file_name": "CLM-2025-02-0026_batch2_acord_fnol.pdf",
  "policy_number": "INFORMATION",
  "claim_number": "POLICY",
  "incident_date": "31/10/2025",
  "description": "generated: 2025-10-31 19:06:28 claim policy information claim id: clm-2025-02-0026 policy no: pol-7748377 claim date: 2025-10-20 loss date: 2025-10-20 claimant information name: kristy allen age: 22 contact: (373)652-2632x99751 address: 45349 angela ford, north brentside, va 42545 vehicle information make/model: maruti corolla (2017) registration: ni 67 ih 3319 odometer: 107311 km declared value: i600,000 incident details on 2025-10-20 at around 16:45, the insured vehicle was stopped at a red light on lowe terrace borough when it was rear-ended by another car. the insured reported minor neck pain and the vehicle s rear bumper and trunk were damaged. location: 81866 rodriguez point suite 030, marcusstad weather: night third party involved: true injuries reported: false police report filed: true police report no: pr-84249 damage estimate damage areas: left mirror, windshield, right door estimated damage cost: i350,000 photos attached: 7 policy coverage coverage: third party deductible: i5,000 policy period: 2025-09-15 to 2026-09-15 previous claims: 1 adjuster notes: signature: date: generated by: syntheticgenerator claim id: clm-2025-02-0026 batch: 2 version: v1",
  "estimated_damage": 202.0,
  "police_report": true,
  "word_count": 164,
  "sentiment": 0.0016,
  "fraud_flag": false,
  "fraud_flags": []
}